oxe_downloader/__init__.py
oxe_downloader/dataset_info.json
oxe_downloader/download.py
oxe_downloader/md5_cache.py
oxe_downloader-0.0.2.dist-info/LICENSE
oxe_downloader-0.0.2.dist-info/METADATA
oxe_downloader-0.0.2.dist-info/WHEEL
oxe_downloader-0.0.2.dist-info/entry_points.txt
oxe_downloader-0.0.2.dist-info/top_level.txt
oxe_downloader-0.0.2.dist-info/RECORD
