Metadata-Version: 2.1
Name: oxe_downloader
Version: 0.0.2
Summary: A tool to download open-x-embodiment datasets from Google Cloud Storage
Home-page: https://github.com/mishmish66/oxe_downloader
Author: Misha Lvovsky
Author-email: m.lvovsky66@gmail.com
Classifier: Programming Language :: Python :: 3
Classifier: License :: OSI Approved :: MIT License
Classifier: Operating System :: OS Independent
Requires-Python: >=3.6
License-File: LICENSE
Requires-Dist: typer
Requires-Dist: google-cloud-storage
Requires-Dist: tqdm
Requires-Dist: typing-extensions
